multivectors.py
multivectors-1.2.1.post0.dist-info/LICENSE
multivectors-1.2.1.post0.dist-info/METADATA
multivectors-1.2.1.post0.dist-info/WHEEL
multivectors-1.2.1.post0.dist-info/top_level.txt
multivectors-1.2.1.post0.dist-info/RECORD
