Metadata-Version: 2.1
Name: multivectors
Version: 1.2.1.post0
Summary: Compute blades and multivectors in arbitrary-dimensional space.
Author: Ken Hilton
License: Apache License
Project-URL: Source, https://github.com/Kenny2github/MultiVectors
Project-URL: Documentation, https://multivectors.rtfd.io
Keywords: multivector,geometric,algebra
Classifier: Development Status :: 4 - Beta
Classifier: License :: OSI Approved :: Apache Software License
Classifier: Intended Audience :: Developers
Classifier: Intended Audience :: Science/Research
Classifier: Topic :: Scientific/Engineering :: Mathematics
Classifier: Topic :: Software Development :: Libraries :: Python Modules
Classifier: Programming Language :: Python :: 3
Classifier: Programming Language :: Python :: 3 :: Only
Classifier: Programming Language :: Python :: 3.7
Classifier: Programming Language :: Python :: 3.8
Classifier: Programming Language :: Python :: 3.9
Classifier: Programming Language :: Python :: 3.10
Classifier: Programming Language :: Python :: 3.11
Classifier: Typing :: Typed
Requires-Python: >=3.7
License-File: LICENSE
Provides-Extra: test
Requires-Dist: pytest ; extra == 'test'
